COPYING
LICENSE.gnu-unifont.txt
MANIFEST.in
README.rst
setup.py
PyDRCS.egg-info/PKG-INFO
PyDRCS.egg-info/SOURCES.txt
PyDRCS.egg-info/dependency_links.txt
PyDRCS.egg-info/eager_resources.txt
PyDRCS.egg-info/entry_points.txt
PyDRCS.egg-info/not-zip-safe
PyDRCS.egg-info/requires.txt
PyDRCS.egg-info/top_level.txt
drcs/__init__.py
drcs/drcs.py
drcs/unifont-5.1.20080907.ttf
drcs/wcwidth.py