Metadata-Version: 1.0
Name: PyDRCS
Version: 0.1.2
Summary: Make DRCS glyphs for DEC VT-series from image files
Home-page: https://github.com/saitoha/PyDRCS
Author: Hayaki Saito (user@zuse.jp)
Author-email: user@zuse.jp
License: GPL v3
Keywords: drcs terminal sixel image
Platform: UNKNOWN
Classifier: Development Status :: 4 - Beta
Classifier: Topic :: Terminals
Classifier: Environment :: Console
Classifier: Intended Audience :: End Users/Desktop
Classifier: License :: OSI Approved :: GNU General Public License (GPL)
Classifier: Programming Language :: Python
